asyncstdlib/__init__.py
asyncstdlib/_core.py
asyncstdlib/_lrucache.py
asyncstdlib/_lrucache.pyi
asyncstdlib/_typing.py
asyncstdlib/_utility.py
asyncstdlib/asynctools.py
asyncstdlib/builtins.py
asyncstdlib/builtins.pyi
asyncstdlib/contextlib.py
asyncstdlib/contextlib.pyi
asyncstdlib/functools.py
asyncstdlib/functools.pyi
asyncstdlib/heapq.py
asyncstdlib/heapq.pyi
asyncstdlib/itertools.py
asyncstdlib/itertools.pyi
asyncstdlib/py.typed
asyncstdlib-3.12.2.dist-info/LICENSE
asyncstdlib-3.12.2.dist-info/WHEEL
asyncstdlib-3.12.2.dist-info/METADATA
asyncstdlib-3.12.2.dist-info/RECORD
