Metadata-Version: 2.1
Name: asyncstdlib
Version: 3.12.2
Summary: The missing async toolbox
Keywords: async,enumerate,itertools,builtins,functools,contextlib
Author-email: Max Fischer <maxfischer2781@gmail.com>
Requires-Python: ~=3.8
Classifier: Development Status :: 5 - Production/Stable
Classifier: Framework :: AsyncIO
Classifier: Intended Audience :: Developers
Classifier: License :: OSI Approved :: MIT License
Classifier: Programming Language :: Python :: 3 :: Only
Classifier: Programming Language :: Python :: 3.8
Classifier: Programming Language :: Python :: 3.9
Classifier: Programming Language :: Python :: 3.10
Classifier: Programming Language :: Python :: 3.11
Classifier: Programming Language :: Python :: 3.12
Requires-Dist: sphinx ; extra == "doc"
Requires-Dist: sphinxcontrib-trio ; extra == "doc"
Requires-Dist: pytest ; extra == "test"
Requires-Dist: flake8 ; extra == "test"
Requires-Dist: flake8-bugbear ; extra == "test"
Requires-Dist: black ; extra == "test" and ( implementation_name=='cpython')
Requires-Dist: coverage ; extra == "test"
Requires-Dist: pytest-cov ; extra == "test"
Requires-Dist: flake8-2020 ; extra == "test"
Requires-Dist: mypy ; extra == "test" and ( implementation_name=='cpython')
Requires-Dist: typing-extensions ; extra == "test"
Project-URL: Documentation, https://asyncstdlib.readthedocs.io/en/latest/
Project-URL: Source, https://github.com/maxfischer2781/asyncstdlib
Provides-Extra: doc
Provides-Extra: test
